zope/locking/README.rst
zope/locking/__init__.py
zope/locking/adapters.py
zope/locking/annoying.rst
zope/locking/cleanup.rst
zope/locking/configure.zcml
zope/locking/ftesting.zcml
zope/locking/generations.py
zope/locking/generations.zcml
zope/locking/interfaces.py
zope/locking/testing.py
zope/locking/tests.py
zope/locking/tokens.py
zope/locking/utility.py
zope/locking/utils.py
zope_locking-4.0.dist-info/licenses/LICENSE.rst
zope_locking-4.0.dist-info/METADATA
zope_locking-4.0.dist-info/WHEEL
zope_locking-4.0.dist-info/top_level.txt
zope_locking-4.0.dist-info/RECORD
