Metadata-Version: 2.4
Name: zope.locking
Version: 4.0
Summary: Advisory exclusive locks, shared locks, and freezes (locked to no-one).
Home-page: https://github.com/zopefoundation/zope.locking
Author: Zope Project
Author-email: zope3-dev@zope.org
License: ZPL-2.1
Classifier: Development Status :: 5 - Production/Stable
Classifier: Environment :: Web Environment
Classifier: Intended Audience :: Developers
Classifier: License :: OSI Approved :: Zope Public License
Classifier: Programming Language :: Python
Classifier: Programming Language :: Python :: 3
Classifier: Programming Language :: Python :: 3.9
Classifier: Programming Language :: Python :: 3.10
Classifier: Programming Language :: Python :: 3.11
Classifier: Programming Language :: Python :: 3.12
Classifier: Programming Language :: Python :: 3.13
Classifier: Programming Language :: Python :: Implementation :: CPython
Classifier: Programming Language :: Python :: Implementation :: PyPy
Classifier: Natural Language :: English
Classifier: Operating System :: OS Independent
Classifier: Topic :: Internet :: WWW/HTTP
Classifier: Framework :: Zope :: 3
Requires-Python: >=3.9
License-File: LICENSE.rst
Requires-Dist: BTrees
Requires-Dist: persistent
Requires-Dist: pytz
Requires-Dist: setuptools
Requires-Dist: zope.component
Requires-Dist: zope.event
Requires-Dist: zope.generations
Requires-Dist: zope.interface>=3.8
Requires-Dist: zope.keyreference
Requires-Dist: zope.location
Requires-Dist: zope.schema
Requires-Dist: zope.security
Provides-Extra: test
Requires-Dist: transaction; extra == "test"
Requires-Dist: zope.app.appsetup; extra == "test"
Requires-Dist: zope.testing; extra == "test"
Requires-Dist: zope.testrunner>=6.4; extra == "test"
Dynamic: author
Dynamic: author-email
Dynamic: classifier
Dynamic: description
Dynamic: home-page
Dynamic: license
Dynamic: license-file
Dynamic: provides-extra
Dynamic: requires-dist
Dynamic: requires-python
Dynamic: summary
